[
    {
        "name": "Y Mentor Training (Pickens YMCA) 11/28/2023",
        "city": "Greenville",
        "startDate": "2023-11-28",
        "endDate": "2023-11-28",
        "date": "2023-11-28",
        "url": "https://www.eventbrite.com/e/y-mentor-training-pickens-ymca-11282023-registration-757904792637",
        "location": {
            "address": {
                "addressCountry": "US",
                "addressLocality": "Pickens",
                "addressRegion": "SC",
                "streetAddress": "2223 Gentry Memorial Hwy",
                "postalCode": "29671",
                "@type": "PostalAddress"
            },
            "geo": {
                "latitude": "34.8579239",
                "@type": "GeoCoordinates",
                "longitude": "-82.67648559999999"
            },
            "@type": "Place",
            "name": "Pickens YMCA"
        },
        "address": {
            "addressCountry": "US",
            "addressLocality": "Pickens",
            "addressRegion": "SC",
            "streetAddress": "2223 Gentry Memorial Hwy",
            "postalCode": "29671",
            "@type": "PostalAddress"
        },
        "description": "Y Mentor Training (Pickens YMCA) 11/28/2023",
        "position": {
            "lat": 34.8579239,
            "lng": -82.67648559999999
        }
    },
    {
        "name": "Y Mentor Training (Powdersville Y) 11/20/2023",
        "city": "Greenville",
        "startDate": "2023-11-20",
        "endDate": "2023-11-20",
        "date": "2023-11-20",
        "url": "https://www.eventbrite.com/e/y-mentor-training-powdersville-y-11202023-registration-757874632427",
        "location": {
            "address": {
                "addressCountry": "US",
                "addressLocality": "Piedmont",
                "addressRegion": "SC",
                "streetAddress": "9115 SC Hwy 81",
                "postalCode": "29673",
                "@type": "PostalAddress"
            },
            "geo": {
                "latitude": "34.7503346",
                "@type": "GeoCoordinates",
                "longitude": "-82.51951389999999"
            },
            "@type": "Place",
            "name": "Powdersville YMCA"
        },
        "address": {
            "addressCountry": "US",
            "addressLocality": "Piedmont",
            "addressRegion": "SC",
            "streetAddress": "9115 SC Hwy 81",
            "postalCode": "29673",
            "@type": "PostalAddress"
        },
        "description": "Y Mentor Training (Powdersville Y)  11/20/2023",
        "position": {
            "lat": 34.7503346,
            "lng": -82.51951389999999
        }
    },
    {
        "name": "Volunteer Advocate Training",
        "city": "Greenville",
        "startDate": "2023-12-05",
        "endDate": "2023-12-05",
        "date": "2023-12-05",
        "url": "https://www.eventbrite.com/e/volunteer-advocate-training-tickets-740094972987",
        "location": {
            "address": {
                "addressCountry": "US",
                "addressLocality": "Greenwood",
                "addressRegion": "SC",
                "streetAddress": "115 East Alexander Avenue",
                "postalCode": "29646",
                "@type": "PostalAddress"
            },
            "geo": {
                "latitude": "34.17894199999999",
                "@type": "GeoCoordinates",
                "longitude": "-82.151382"
            },
            "@type": "Place",
            "name": "Beyond Abuse"
        },
        "address": {
            "addressCountry": "US",
            "addressLocality": "Greenwood",
            "addressRegion": "SC",
            "streetAddress": "115 East Alexander Avenue",
            "postalCode": "29646",
            "@type": "PostalAddress"
        },
        "description": "Beyond Abuse offers training for volunteer advocates who wish to help those impacted by sexual violence and child abuse.",
        "position": {
            "lat": 34.17894199999999,
            "lng": -82.151382
        }
    },
    {
        "name": "Y Mentor Training (Easley, Corporate Office) 11/21/2023",
        "city": "Greenville",
        "startDate": "2023-11-21",
        "endDate": "2023-11-21",
        "date": "2023-11-21",
        "url": "https://www.eventbrite.com/e/y-mentor-training-easley-corporate-office-11212023-registration-757873940357",
        "location": {
            "address": {
                "addressCountry": "US",
                "addressLocality": "Easley",
                "addressRegion": "SC",
                "streetAddress": "101 Burns Rd",
                "postalCode": "29640",
                "@type": "PostalAddress"
            },
            "geo": {
                "latitude": "34.8299499",
                "@type": "GeoCoordinates",
                "longitude": "-82.5787214"
            },
            "@type": "Place",
            "name": "Easley *Corporate Office*"
        },
        "address": {
            "addressCountry": "US",
            "addressLocality": "Easley",
            "addressRegion": "SC",
            "streetAddress": "101 Burns Rd",
            "postalCode": "29640",
            "@type": "PostalAddress"
        },
        "description": "Y Mentor Training (Easley, Corporate Office) 11/21/2023",
        "position": {
            "lat": 34.8299499,
            "lng": -82.5787214
        }
    },
    {
        "name": "People with Purpose Volunteer Orientation",
        "city": "Greenville",
        "startDate": "2023-12-14",
        "endDate": "2023-12-14",
        "date": "2023-12-14",
        "url": "https://www.eventbrite.com/e/people-with-purpose-volunteer-orientation-registration-465143134637",
        "location": {
            "address": {
                "addressCountry": "US",
                "addressLocality": "Swannanoa",
                "addressRegion": "NC",
                "streetAddress": "West Campus Dining Hall",
                "postalCode": "28778",
                "@type": "PostalAddress"
            },
            "geo": {
                "latitude": "35.6187798",
                "@type": "GeoCoordinates",
                "longitude": "-82.37809299999999"
            },
            "@type": "Place",
            "name": "Black Mountain Home"
        },
        "address": {
            "addressCountry": "US",
            "addressLocality": "Swannanoa",
            "addressRegion": "NC",
            "streetAddress": "West Campus Dining Hall",
            "postalCode": "28778",
            "@type": "PostalAddress"
        },
        "description": "PEOPLE WITH PURPOSE are healthier, happier, and live longer! Join our volunteer team and find your purpose by helping children.",
        "position": {
            "lat": 35.6187798,
            "lng": -82.37809299999999
        }
    },
    {
        "name": "Tamin Temple #155 Annual Charity Ball",
        "city": "Greenville",
        "startDate": "2023-11-24",
        "endDate": "2023-11-24",
        "date": "2023-11-24",
        "url": "https://www.eventbrite.com/e/tamin-temple-155-annual-charity-ball-tickets-742109217647",
        "location": {
            "address": {
                "addressCountry": "US",
                "addressLocality": "Lyman",
                "addressRegion": "SC",
                "streetAddress": "198 Spartanburg Highway",
                "postalCode": "29365",
                "@type": "PostalAddress"
            },
            "geo": {
                "latitude": "34.9544211",
                "@type": "GeoCoordinates",
                "longitude": "-82.1191982"
            },
            "@type": "Place",
            "name": "Nara Hall, Spartanburg Highway, Lyman, SC, USA"
        },
        "address": {
            "addressCountry": "US",
            "addressLocality": "Lyman",
            "addressRegion": "SC",
            "streetAddress": "198 Spartanburg Highway",
            "postalCode": "29365",
            "@type": "PostalAddress"
        },
        "description": "Get ready to groove at the Tamin Temple #155 Annual Charity Ball, where we'll dance, fellowship, and donate to make a difference in style!",
        "position": {
            "lat": 34.9544211,
            "lng": -82.1191982
        }
    },
    {
        "name": "Arts and Blues",
        "city": "Greenville",
        "startDate": "2023-11-30",
        "endDate": "2023-11-30",
        "date": "2023-11-30",
        "url": "https://www.eventbrite.com/e/arts-and-blues-tickets-726731983927",
        "location": {
            "address": {
                "addressCountry": "US",
                "addressLocality": "Spartanburg",
                "addressRegion": "SC",
                "streetAddress": "1129 Woodburn Road",
                "postalCode": "29302",
                "@type": "PostalAddress"
            },
            "geo": {
                "latitude": "34.947601",
                "@type": "GeoCoordinates",
                "longitude": "-81.8962849"
            },
            "@type": "Place",
            "name": "At the home of Hallie and Chip Hurst"
        },
        "address": {
            "addressCountry": "US",
            "addressLocality": "Spartanburg",
            "addressRegion": "SC",
            "streetAddress": "1129 Woodburn Road",
            "postalCode": "29302",
            "@type": "PostalAddress"
        },
        "description": "A benefit for the National Alliance on Mental Illness (NAMI) Spartanburg Chapter. Come help us make Spartanburg “Stigma Free”!",
        "position": {
            "lat": 34.947601,
            "lng": -81.8962849
        }
    },
    {
        "name": "Byrdie Wilson’s “Where My Roots Run Tour” Fundraiser Benefiting AFSPSC",
        "city": "Greenville",
        "startDate": "2023-12-19",
        "endDate": "2023-12-19",
        "date": "2023-12-19",
        "url": "https://www.eventbrite.com/e/byrdie-wilsons-where-my-roots-run-tour-fundraiser-benefiting-afspsc-tickets-754307834037",
        "location": {
            "address": {
                "addressCountry": "US",
                "addressLocality": "Greenville",
                "addressRegion": "SC",
                "streetAddress": "1 East Coffee Street",
                "postalCode": "29601",
                "@type": "PostalAddress"
            },
            "geo": {
                "latitude": "34.85156759999999",
                "@type": "GeoCoordinates",
                "longitude": "-82.3982716"
            },
            "@type": "Place",
            "name": "Coffee Underground, East Coffee Street, Greenville, SC, USA"
        },
        "address": {
            "addressCountry": "US",
            "addressLocality": "Greenville",
            "addressRegion": "SC",
            "streetAddress": "1 East Coffee Street",
            "postalCode": "29601",
            "@type": "PostalAddress"
        },
        "description": "Join us for a night of music and storytelling as we come together to support a cause close to our hearts.",
        "position": {
            "lat": 34.85156759999999,
            "lng": -82.3982716
        }
    },
    {
        "name": "SHARE'S ANNUAL GALA",
        "city": "Greenville",
        "startDate": "2024-02-29",
        "endDate": "2024-02-29",
        "date": "2024-02-29",
        "url": "https://www.eventbrite.com/e/shares-annual-gala-tickets-761260529737",
        "location": {
            "address": {
                "addressCountry": "US",
                "addressLocality": "Greenville",
                "addressRegion": "SC",
                "streetAddress": "1 Exposition Drive",
                "postalCode": "29607",
                "@type": "PostalAddress"
            },
            "geo": {
                "latitude": "34.8521853",
                "@type": "GeoCoordinates",
                "longitude": "-82.3542866"
            },
            "@type": "Place",
            "name": "Greenville Convention Center"
        },
        "address": {
            "addressCountry": "US",
            "addressLocality": "Greenville",
            "addressRegion": "SC",
            "streetAddress": "1 Exposition Drive",
            "postalCode": "29607",
            "@type": "PostalAddress"
        },
        "description": "Fundraiser to help SHARE build stronger families and create vibrant communities. Meet great people, eat good food, and dance the night away.",
        "position": {
            "lat": 34.8521853,
            "lng": -82.3542866
        }
    },
    {
        "name": "NOLA Network Annual Mardi Gras Fundraiser 2024",
        "city": "Greenville",
        "startDate": "2024-02-24",
        "endDate": "2024-02-24",
        "date": "2024-02-24",
        "url": "https://www.eventbrite.com/e/nola-network-annual-mardi-gras-fundraiser-2024-tickets-748833881297",
        "location": {
            "address": {
                "addressCountry": "US",
                "addressLocality": "Clemson",
                "addressRegion": "SC",
                "streetAddress": "1310 Tiger Boulevard",
                "postalCode": "29631",
                "@type": "PostalAddress"
            },
            "geo": {
                "latitude": "34.6882307",
                "@type": "GeoCoordinates",
                "longitude": "-82.8251928"
            },
            "@type": "Place",
            "name": "Best Western Plus Clemson Hotel & Conference Center"
        },
        "address": {
            "addressCountry": "US",
            "addressLocality": "Clemson",
            "addressRegion": "SC",
            "streetAddress": "1310 Tiger Boulevard",
            "postalCode": "29631",
            "@type": "PostalAddress"
        },
        "description": "The NOLA Network will host its 3rd annual Mardi Gras Gala Fundraiser in Clemson.",
        "position": {
            "lat": 34.6882307,
            "lng": -82.8251928
        }
    },
    {
        "name": "EXHIBITION-The Art of Hope: Through the Eyes of a Child",
        "city": "Greenville",
        "startDate": "2023-11-28",
        "endDate": "2023-11-28",
        "date": "2023-11-28",
        "url": "https://www.eventbrite.com/e/exhibition-the-art-of-hope-through-the-eyes-of-a-child-tickets-758944632827",
        "location": {
            "address": {
                "addressCountry": "US",
                "addressLocality": "Spartanburg",
                "addressRegion": "SC",
                "streetAddress": "146 East Main Street",
                "postalCode": "29306",
                "@type": "PostalAddress"
            },
            "geo": {
                "latitude": "34.9502059",
                "@type": "GeoCoordinates",
                "longitude": "-81.93015749999999"
            },
            "@type": "Place",
            "name": "146 E Main St"
        },
        "address": {
            "addressCountry": "US",
            "addressLocality": "Spartanburg",
            "addressRegion": "SC",
            "streetAddress": "146 East Main Street",
            "postalCode": "29306",
            "@type": "PostalAddress"
        },
        "description": "Hope Center for Children’s \"The Art of Hope: Through the Eyes of a Child\" exhibit showcases impactful art created by our youth residents.",
        "position": {
            "lat": 34.9502059,
            "lng": -81.93015749999999
        }
    },
    {
        "name": "Young Adults Community Service Meetup",
        "city": "Greenville",
        "startDate": "2023-11-28",
        "endDate": "2023-11-28",
        "date": "2023-11-28",
        "url": "https://www.eventbrite.com/e/young-adults-community-service-meetup-tickets-760709501597",
        "location": {
            "address": {
                "addressCountry": "US",
                "addressLocality": "Simpsonville",
                "addressRegion": "SC",
                "streetAddress": "1102 Howard Drive",
                "postalCode": "29681",
                "@type": "PostalAddress"
            },
            "geo": {
                "latitude": "34.716491",
                "@type": "GeoCoordinates",
                "longitude": "-82.21778499999999"
            },
            "@type": "Place",
            "name": "Center For Community Services"
        },
        "address": {
            "addressCountry": "US",
            "addressLocality": "Simpsonville",
            "addressRegion": "SC",
            "streetAddress": "1102 Howard Drive",
            "postalCode": "29681",
            "@type": "PostalAddress"
        },
        "description": "Make a difference with other young professionals",
        "position": {
            "lat": 34.716491,
            "lng": -82.21778499999999
        }
    },
    {
        "name": "HCC Foundation Presents Blue Ridge Orchestra's Unwrapping Holiday Favorites",
        "city": "Greenville",
        "startDate": "2023-12-09",
        "endDate": "2023-12-09",
        "date": "2023-12-09",
        "url": "https://www.eventbrite.com/e/hcc-foundation-presents-blue-ridge-orchestras-unwrapping-holiday-favorites-tickets-636537279137",
        "location": {
            "address": {
                "addressCountry": "US",
                "addressLocality": "Clyde",
                "addressRegion": "NC",
                "streetAddress": "185 Freedlander Drive",
                "postalCode": "28721",
                "@type": "PostalAddress"
            },
            "geo": {
                "latitude": "35.5259088",
                "@type": "GeoCoordinates",
                "longitude": "-82.92788639999999"
            },
            "@type": "Place",
            "name": "Haywood Community College"
        },
        "address": {
            "addressCountry": "US",
            "addressLocality": "Clyde",
            "addressRegion": "NC",
            "streetAddress": "185 Freedlander Drive",
            "postalCode": "28721",
            "@type": "PostalAddress"
        },
        "description": "Haywood Community College Foundation's Haywood Strong Scholarship Fundraiser brings you an afternoon of Holiday Favorites.",
        "position": {
            "lat": 35.5259088,
            "lng": -82.92788639999999
        }
    },
    {
        "name": "PowHer + Potential Leadership Retreat: Asheville, NC",
        "city": "Greenville",
        "startDate": "2024-05-03",
        "endDate": "2024-05-05",
        "date": "2024-05-03 - 2024-05-05",
        "url": "https://www.eventbrite.com/e/powher-potential-leadership-retreat-asheville-nc-registration-726468154807",
        "location": {
            "address": {
                "addressCountry": "US",
                "addressLocality": "Asheville",
                "addressRegion": "NC",
                "streetAddress": "Location TBA by January 2024",
                "postalCode": "28801",
                "@type": "PostalAddress"
            },
            "geo": {
                "latitude": "35.5950581",
                "@type": "GeoCoordinates",
                "longitude": "-82.5514869"
            },
            "@type": "Place",
            "name": "Asheville, NC: Location TBA"
        },
        "address": {
            "addressCountry": "US",
            "addressLocality": "Asheville",
            "addressRegion": "NC",
            "streetAddress": "Location TBA by January 2024",
            "postalCode": "28801",
            "@type": "PostalAddress"
        },
        "description": "Get ready to be inspired, empowered, and motivated as we come together to unlock our true potential in a retreat setting",
        "position": {
            "lat": 35.5950581,
            "lng": -82.5514869
        }
    },
    {
        "name": "AMS Silent Auction",
        "city": "Greenville",
        "startDate": "2023-12-07",
        "endDate": "2023-12-07",
        "date": "2023-12-07",
        "url": "https://www.eventbrite.com/e/ams-silent-auction-tickets-741784004927",
        "location": {
            "address": {
                "addressCountry": "US",
                "addressLocality": "Asheville",
                "addressRegion": "NC",
                "streetAddress": "174 Broadway Street",
                "postalCode": "28801",
                "@type": "PostalAddress"
            },
            "geo": {
                "latitude": "35.6005152",
                "@type": "GeoCoordinates",
                "longitude": "-82.55497419999999"
            },
            "@type": "Place",
            "name": "Archetype Brewing - North (Tap Lounge + Venue), Broadway Street, Asheville, NC, USA"
        },
        "address": {
            "addressCountry": "US",
            "addressLocality": "Asheville",
            "addressRegion": "NC",
            "streetAddress": "174 Broadway Street",
            "postalCode": "28801",
            "@type": "PostalAddress"
        },
        "description": "Get ready for the AMS Silent Auction, a fun-filled in-person event where you can bid on amazing items while enjoying a lively atmosphere.",
        "position": {
            "lat": 35.6005152,
            "lng": -82.55497419999999
        }
    },
    {
        "name": "Nature-Based Wellness Retreat for Military Widows",
        "city": "Greenville",
        "startDate": "2024-06-06",
        "endDate": "2024-06-09",
        "date": "2024-06-06 - 2024-06-09",
        "url": "https://www.eventbrite.com/e/nature-based-wellness-retreat-for-military-widows-tickets-748533974267",
        "location": {
            "address": {
                "addressCountry": "US",
                "addressLocality": "Franklin",
                "addressRegion": "NC",
                "streetAddress": "635 Berry Cove Rd.",
                "postalCode": "28734",
                "@type": "PostalAddress"
            },
            "geo": {
                "latitude": "35.212513",
                "@type": "GeoCoordinates",
                "longitude": "-83.30076299999999"
            },
            "@type": "Place",
            "name": "Nurture + Nature Glamping Retreat Center"
        },
        "address": {
            "addressCountry": "US",
            "addressLocality": "Franklin",
            "addressRegion": "NC",
            "streetAddress": "635 Berry Cove Rd.",
            "postalCode": "28734",
            "@type": "PostalAddress"
        },
        "description": "Get ready for a rejuvenating getaway at our Nature-Based Wellness Retreat, exclusively designed for military widows to find support and grow",
        "position": {
            "lat": 35.212513,
            "lng": -83.30076299999999
        }
    },
    {
        "name": "ABCLT Annual Membership Meeting",
        "city": "Greenville",
        "startDate": "2023-12-11",
        "endDate": "2023-12-11",
        "date": "2023-12-11",
        "url": "https://www.eventbrite.com/e/abclt-annual-membership-meeting-tickets-760742510327",
        "location": {
            "address": {
                "addressCountry": "US",
                "addressLocality": "Asheville",
                "addressRegion": "NC",
                "streetAddress": "90 Southside Ave",
                "postalCode": "28801",
                "@type": "PostalAddress"
            },
            "geo": {
                "latitude": "35.5860166",
                "@type": "GeoCoordinates",
                "longitude": "-82.55523579999999"
            },
            "@type": "Place",
            "name": "ABCLT Office"
        },
        "address": {
            "addressCountry": "US",
            "addressLocality": "Asheville",
            "addressRegion": "NC",
            "streetAddress": "90 Southside Ave",
            "postalCode": "28801",
            "@type": "PostalAddress"
        },
        "description": "Join us to celebrate what ABCLT accomplished in 2023 and learn what we have planned for 2024. this year and what's to come in 2023!",
        "position": {
            "lat": 35.5860166,
            "lng": -82.55523579999999
        }
    },
    {
        "name": "Every Black Voice: ACNC Hosts AVL's Racial Justice Coalition Lunch n' Learn",
        "city": "Greenville",
        "startDate": "2023-12-27",
        "endDate": "2023-12-27",
        "date": "2023-12-27",
        "url": "https://www.eventbrite.com/e/every-black-voice-acnc-hosts-avls-racial-justice-coalition-lunch-n-learn-tickets-643335984247",
        "location": {
            "address": {
                "addressCountry": "US",
                "addressLocality": "Asheville",
                "addressRegion": "NC",
                "streetAddress": "216 Asheland Avenue",
                "postalCode": "28801",
                "@type": "PostalAddress"
            },
            "geo": {
                "latitude": "35.5862181",
                "@type": "GeoCoordinates",
                "longitude": "-82.5559073"
            },
            "@type": "Place",
            "name": "216 Asheland Ave"
        },
        "address": {
            "addressCountry": "US",
            "addressLocality": "Asheville",
            "addressRegion": "NC",
            "streetAddress": "216 Asheland Avenue",
            "postalCode": "28801",
            "@type": "PostalAddress"
        },
        "description": "ACNC is excited to be a part of NC Managed Care. Our goal is to help people get care, stay well and build healthy communities.",
        "position": {
            "lat": 35.5862181,
            "lng": -82.5559073
        }
    },
    {
        "name": "Volunteer Event",
        "city": "Greenville",
        "startDate": "2023-12-16",
        "endDate": "2023-12-16",
        "date": "2023-12-16",
        "url": "https://www.eventbrite.com/e/volunteer-event-tickets-757531596397",
        "location": {
            "address": {
                "addressCountry": "US",
                "addressLocality": "Charlotte",
                "addressRegion": "NC",
                "streetAddress": "500-A Spratt Street",
                "postalCode": "28206",
                "@type": "PostalAddress"
            },
            "geo": {
                "latitude": "35.2384999",
                "@type": "GeoCoordinates",
                "longitude": "-80.8378271"
            },
            "@type": "Place",
            "name": "Crisis Assistance Ministry"
        },
        "address": {
            "addressCountry": "US",
            "addressLocality": "Charlotte",
            "addressRegion": "NC",
            "streetAddress": "500-A Spratt Street",
            "postalCode": "28206",
            "@type": "PostalAddress"
        },
        "description": "Join NBMBAA for a volunteer event at the Crisis Assistance Ministry.",
        "position": {
            "lat": 35.2384999,
            "lng": -80.8378271
        }
    },
    {
        "name": "Annual Charity Gala",
        "city": "Greenville",
        "startDate": "2023-12-16",
        "endDate": "2023-12-16",
        "date": "2023-12-16",
        "url": "https://www.eventbrite.com/e/annual-charity-gala-tickets-744441784417",
        "location": {
            "address": {
                "addressCountry": "US",
                "addressLocality": "Rock Hill",
                "addressRegion": "SC",
                "streetAddress": "742 North Anderson Road",
                "postalCode": "29730",
                "@type": "PostalAddress"
            },
            "geo": {
                "latitude": "34.9572439",
                "@type": "GeoCoordinates",
                "longitude": "-80.99517929999999"
            },
            "@type": "Place",
            "name": "742 North Anderson Road, Rock Hill, SC, USA"
        },
        "address": {
            "addressCountry": "US",
            "addressLocality": "Rock Hill",
            "addressRegion": "SC",
            "streetAddress": "742 North Anderson Road",
            "postalCode": "29730",
            "@type": "PostalAddress"
        },
        "description": "Join us for the Annual Charity Gala, an unforgettable evening of giving, glitz, and glamour, where we come together to make a difference in",
        "position": {
            "lat": 34.9572439,
            "lng": -80.99517929999999
        }
    },
    {
        "name": "Charleston Natural History Society Oyster Roast",
        "city": "Charleston",
        "startDate": "2023-12-03",
        "endDate": "2023-12-03",
        "date": "2023-12-03",
        "url": "https://www.eventbrite.com/e/charleston-natural-history-society-oyster-roast-tickets-752884998297",
        "location": {
            "address": {
                "addressCountry": "US",
                "addressLocality": "Charleston",
                "addressRegion": "SC",
                "streetAddress": "1870 Bowens Island Road",
                "postalCode": "29412",
                "@type": "PostalAddress"
            },
            "geo": {
                "latitude": "32.6753683",
                "@type": "GeoCoordinates",
                "longitude": "-79.9646388"
            },
            "@type": "Place",
            "name": "Bowens Island Restaurant, Bowens Island Road, Charleston, SC, USA"
        },
        "address": {
            "addressCountry": "US",
            "addressLocality": "Charleston",
            "addressRegion": "SC",
            "streetAddress": "1870 Bowens Island Road",
            "postalCode": "29412",
            "@type": "PostalAddress"
        },
        "description": "Join us for our Oyster Roast and annual holiday party! Oysters, Chili, Hot Dogs, bird nerds, silent auction, and general merriment!",
        "position": {
            "lat": 32.6753683,
            "lng": -79.9646388
        }
    },
    {
        "name": "Community Grief Circle",
        "city": "Charleston",
        "startDate": "2023-11-29",
        "endDate": "2023-11-29",
        "date": "2023-11-29",
        "url": "https://www.eventbrite.com/e/community-grief-circle-tickets-756278337867",
        "location": {
            "address": {
                "addressCountry": "US",
                "addressLocality": "Charleston",
                "addressRegion": "SC",
                "streetAddress": "349 Folly Road",
                "postalCode": "29412",
                "@type": "PostalAddress"
            },
            "geo": {
                "latitude": "32.7569328",
                "@type": "GeoCoordinates",
                "longitude": "-79.9734022"
            },
            "@type": "Place",
            "name": "Soul + Fire"
        },
        "address": {
            "addressCountry": "US",
            "addressLocality": "Charleston",
            "addressRegion": "SC",
            "streetAddress": "349 Folly Road",
            "postalCode": "29412",
            "@type": "PostalAddress"
        },
        "description": "Together we will move, connect, breath and rest in community.",
        "position": {
            "lat": 32.7569328,
            "lng": -79.9734022
        }
    },
    {
        "name": "David Aylor  Annual Christmas Party & Fundraiser",
        "city": "Charleston",
        "startDate": "2023-12-15",
        "endDate": "2023-12-15",
        "date": "2023-12-15",
        "url": "https://www.eventbrite.com/e/david-aylor-annual-christmas-party-fundraiser-tickets-749452541727",
        "location": {
            "address": {
                "addressCountry": "US",
                "addressLocality": "Charleston",
                "addressRegion": "SC",
                "streetAddress": "462 King St",
                "postalCode": "29403",
                "@type": "PostalAddress"
            },
            "geo": {
                "latitude": "32.7894124",
                "@type": "GeoCoordinates",
                "longitude": "-79.93871769999998"
            },
            "@type": "Place",
            "name": "Republic Garden & Lounge"
        },
        "address": {
            "addressCountry": "US",
            "addressLocality": "Charleston",
            "addressRegion": "SC",
            "streetAddress": "462 King St",
            "postalCode": "29403",
            "@type": "PostalAddress"
        },
        "description": "Join us for the David Aylor Annual Christmas Party & Fundraiser, Friday, December 15th, 2023 from 7-10pm at Republic Garden & Lounge.",
        "position": {
            "lat": 32.7894124,
            "lng": -79.93871769999998
        }
    },
    {
        "name": "BE Impactful Holiday Festival  -  Toy & Dinner Giveaway",
        "city": "Charleston",
        "startDate": "2023-12-16",
        "endDate": "2023-12-16",
        "date": "2023-12-16",
        "url": "https://www.eventbrite.com/e/be-impactful-holiday-festival-toy-dinner-giveaway-registration-741007331877",
        "location": {
            "address": {
                "addressCountry": "US",
                "addressLocality": "North Charleston",
                "addressRegion": "SC",
                "streetAddress": "1995 Bolton Street",
                "postalCode": "29406",
                "@type": "PostalAddress"
            },
            "geo": {
                "latitude": "32.8808776",
                "@type": "GeoCoordinates",
                "longitude": "-80.0031688"
            },
            "@type": "Place",
            "name": "Ferndale Community Center"
        },
        "address": {
            "addressCountry": "US",
            "addressLocality": "North Charleston",
            "addressRegion": "SC",
            "streetAddress": "1995 Bolton Street",
            "postalCode": "29406",
            "@type": "PostalAddress"
        },
        "description": "BE Impactful presents a Holiday Community Festival & Toy Giveaway. FREE food, music, and games",
        "position": {
            "lat": 32.8808776,
            "lng": -80.0031688
        }
    },
    {
        "name": "2023 Summerville Exchange Club Oyster Roast",
        "city": "Charleston",
        "startDate": "2023-12-09",
        "endDate": "2023-12-09",
        "date": "2023-12-09",
        "url": "https://www.eventbrite.com/e/2023-summerville-exchange-club-oyster-roast-tickets-742820394797",
        "location": {
            "address": {
                "addressCountry": "US",
                "addressLocality": "Summerville",
                "addressRegion": "SC",
                "streetAddress": "400 Country Club Boulevard",
                "postalCode": "29483",
                "@type": "PostalAddress"
            },
            "geo": {
                "latitude": "32.9984255",
                "@type": "GeoCoordinates",
                "longitude": "-80.2018367"
            },
            "@type": "Place",
            "name": "Summerville Country Club"
        },
        "address": {
            "addressCountry": "US",
            "addressLocality": "Summerville",
            "addressRegion": "SC",
            "streetAddress": "400 Country Club Boulevard",
            "postalCode": "29483",
            "@type": "PostalAddress"
        },
        "description": "Join the Summerville Exchange Club for the 2nd Annual Oyster Roast benefitting SHS Cheer and local Youth Programs.",
        "position": {
            "lat": 32.9984255,
            "lng": -80.2018367
        }
    },
    {
        "name": "ECCO's 2023 Adopt-A-Family Program",
        "city": "Charleston",
        "startDate": "2023-12-04",
        "endDate": "2023-12-16",
        "date": "2023-12-04 - 2023-12-16",
        "url": "https://www.eventbrite.com/e/eccos-2023-adopt-a-family-program-registration-748722929437",
        "location": {
            "address": {
                "addressCountry": "US",
                "addressLocality": "Mount Pleasant",
                "addressRegion": "SC",
                "streetAddress": "1145 Six Mile Road",
                "postalCode": "29466",
                "@type": "PostalAddress"
            },
            "geo": {
                "latitude": "32.8400334",
                "@type": "GeoCoordinates",
                "longitude": "-79.81587329999999"
            },
            "@type": "Place",
            "name": "TBD"
        },
        "address": {
            "addressCountry": "US",
            "addressLocality": "Mount Pleasant",
            "addressRegion": "SC",
            "streetAddress": "1145 Six Mile Road",
            "postalCode": "29466",
            "@type": "PostalAddress"
        },
        "description": "16th Annual Adopt-A-Family",
        "position": {
            "lat": 32.8400334,
            "lng": -79.81587329999999
        }
    },
    {
        "name": "Savannah Jaycees Cornhole Tournament",
        "city": "Charleston",
        "startDate": "2023-12-09",
        "endDate": "2023-12-09",
        "date": "2023-12-09",
        "url": "https://www.eventbrite.com/e/savannah-jaycees-cornhole-tournament-tickets-756372339027",
        "location": {
            "address": {
                "addressCountry": "US",
                "addressLocality": "Tybee Island",
                "addressRegion": "GA",
                "streetAddress": "30 Van Horne Avenue",
                "postalCode": "31328",
                "@type": "PostalAddress"
            },
            "geo": {
                "latitude": "32.0177952",
                "@type": "GeoCoordinates",
                "longitude": "-80.8450685"
            },
            "@type": "Place",
            "name": "Jaycee Park"
        },
        "address": {
            "addressCountry": "US",
            "addressLocality": "Tybee Island",
            "addressRegion": "GA",
            "streetAddress": "30 Van Horne Avenue",
            "postalCode": "31328",
            "@type": "PostalAddress"
        },
        "description": "It's the 2nd Annual Savannah Jaycees Cornhole Tournament - join us for a fun, family-friendly competition!",
        "position": {
            "lat": 32.0177952,
            "lng": -80.8450685
        }
    },
    {
        "name": "New Neighbors Community Service at Second Harvest",
        "city": "Charleston",
        "startDate": "2023-11-21",
        "endDate": "2023-11-21",
        "date": "2023-11-21",
        "url": "https://www.eventbrite.com/e/new-neighbors-community-service-at-second-harvest-tickets-699022383767",
        "location": {
            "address": {
                "addressCountry": "US",
                "addressLocality": "Savannah",
                "addressRegion": "GA",
                "streetAddress": "2651 Causton Bluff Road",
                "postalCode": "31404",
                "@type": "PostalAddress"
            },
            "geo": {
                "latitude": "32.064708",
                "@type": "GeoCoordinates",
                "longitude": "-81.045979"
            },
            "@type": "Place",
            "name": "Second Harvest Volunteer Center"
        },
        "address": {
            "addressCountry": "US",
            "addressLocality": "Savannah",
            "addressRegion": "GA",
            "streetAddress": "2651 Causton Bluff Road",
            "postalCode": "31404",
            "@type": "PostalAddress"
        },
        "description": "Volunteer to support America's Second Harvest of Coastal Georgia",
        "position": {
            "lat": 32.064708,
            "lng": -81.045979
        }
    },
    {
        "name": "Charity Uncorked: Cheers for Gilliard & Co",
        "city": "Charleston",
        "startDate": "2023-12-01",
        "endDate": "2023-12-01",
        "date": "2023-12-01",
        "url": "https://www.eventbrite.com/e/charity-uncorked-cheers-for-gilliard-co-tickets-730839770427",
        "location": {
            "address": {
                "addressCountry": "US",
                "addressLocality": "Savannah",
                "addressRegion": "GA",
                "streetAddress": "7054 Hodgson Memorial Drive",
                "postalCode": "31406",
                "@type": "PostalAddress"
            },
            "geo": {
                "latitude": "32.0099569",
                "@type": "GeoCoordinates",
                "longitude": "-81.1083773"
            },
            "@type": "Place",
            "name": "The Narra Tree, Hodgson Memorial Drive, Savannah, GA, USA"
        },
        "address": {
            "addressCountry": "US",
            "addressLocality": "Savannah",
            "addressRegion": "GA",
            "streetAddress": "7054 Hodgson Memorial Drive",
            "postalCode": "31406",
            "@type": "PostalAddress"
        },
        "description": "Get ready to sip, savor, and support a great cause at Charity Uncorked: Cheers for a Cause, where we uncork the power of giving.",
        "position": {
            "lat": 32.0099569,
            "lng": -81.1083773
        }
    },
    {
        "name": "Santa Paws",
        "city": "Charleston",
        "startDate": "2023-12-10",
        "endDate": "2023-12-10",
        "date": "2023-12-10",
        "url": "https://www.eventbrite.com/e/santa-paws-tickets-751707386027",
        "location": {
            "address": {
                "addressCountry": "US",
                "addressLocality": "Savannah",
                "addressRegion": "GA",
                "streetAddress": "1 Resort Drive",
                "postalCode": "31421",
                "@type": "PostalAddress"
            },
            "geo": {
                "latitude": "32.083337",
                "@type": "GeoCoordinates",
                "longitude": "-81.08529399999999"
            },
            "@type": "Place",
            "name": "The Westin Savannah Harbor Golf Resort & Spa"
        },
        "address": {
            "addressCountry": "US",
            "addressLocality": "Savannah",
            "addressRegion": "GA",
            "streetAddress": "1 Resort Drive",
            "postalCode": "31421",
            "@type": "PostalAddress"
        },
        "description": "FREE, NO TICKET REQUIRED: Professional Photos with Santa with pets, kids, or both!",
        "position": {
            "lat": 32.083337,
            "lng": -81.08529399999999
        }
    },
    {
        "name": "Tranquility Transitional Housing First Aunnual Public Benefit Fundraiser",
        "city": "Charleston",
        "startDate": "2023-11-24",
        "endDate": "2023-11-25",
        "date": "2023-11-24 - 2023-11-25",
        "url": "https://www.eventbrite.com/e/tranquility-transitional-housing-first-aunnual-public-benefit-fundraiser-tickets-738292351297",
        "location": {
            "address": {
                "addressCountry": "US",
                "addressLocality": "Gadsden",
                "addressRegion": "SC",
                "streetAddress": "1032 George Wilson Boulevard",
                "postalCode": "29052",
                "@type": "PostalAddress"
            },
            "geo": {
                "latitude": "33.8244251",
                "@type": "GeoCoordinates",
                "longitude": "-80.70178179999999"
            },
            "@type": "Place",
            "name": "1032 George Wilson Blvd"
        },
        "address": {
            "addressCountry": "US",
            "addressLocality": "Gadsden",
            "addressRegion": "SC",
            "streetAddress": "1032 George Wilson Boulevard",
            "postalCode": "29052",
            "@type": "PostalAddress"
        },
        "description": "The purpose of this fundraiser event is to build a facility for housing and educate and decriminalized ex offenders.",
        "position": {
            "lat": 33.8244251,
            "lng": -80.70178179999999
        }
    },
    {
        "name": "Women Blessing Women Empowerment Conference",
        "city": "Charleston",
        "startDate": "2023-12-08",
        "endDate": "2023-12-09",
        "date": "2023-12-08 - 2023-12-09",
        "url": "https://www.eventbrite.com/e/women-blessing-women-empowerment-conference-tickets-762846643847",
        "location": {
            "address": {
                "addressCountry": "US",
                "addressLocality": "Savannah",
                "addressRegion": "GA",
                "streetAddress": "601 East Bay Street",
                "postalCode": "31401",
                "@type": "PostalAddress"
            },
            "geo": {
                "latitude": "32.078895",
                "@type": "GeoCoordinates",
                "longitude": "-81.08502039999999"
            },
            "@type": "Place",
            "name": "Kimpton Brice Hotel"
        },
        "address": {
            "addressCountry": "US",
            "addressLocality": "Savannah",
            "addressRegion": "GA",
            "streetAddress": "601 East Bay Street",
            "postalCode": "31401",
            "@type": "PostalAddress"
        },
        "description": "Join us at the Women Blessing Women Empowerment Conference, December 8th & 9th 2023, where powerful women come together to uplift, inspire.",
        "position": {
            "lat": 32.078895,
            "lng": -81.08502039999999
        }
    },
    {
        "name": "Love Gives Gala",
        "city": "Charleston",
        "startDate": "2024-02-08",
        "endDate": "2024-02-08",
        "date": "2024-02-08",
        "url": "https://www.eventbrite.com/e/love-gives-gala-tickets-742696754987",
        "location": {
            "address": {
                "addressCountry": "US",
                "addressLocality": "Savannah",
                "addressRegion": "GA",
                "streetAddress": "601 Cohen Street",
                "postalCode": "31401",
                "@type": "PostalAddress"
            },
            "geo": {
                "latitude": "32.0724694",
                "@type": "GeoCoordinates",
                "longitude": "-81.10291889999999"
            },
            "@type": "Place",
            "name": "Savannah Station"
        },
        "address": {
            "addressCountry": "US",
            "addressLocality": "Savannah",
            "addressRegion": "GA",
            "streetAddress": "601 Cohen Street",
            "postalCode": "31401",
            "@type": "PostalAddress"
        },
        "description": "Unlocking Hearts, Changing Futures: Love Gives Gala for Operation Kid Forward",
        "position": {
            "lat": 32.0724694,
            "lng": -81.10291889999999
        }
    },
    {
        "name": "24K MAGIC  HOLIDAY EXTRAVAGAZZA",
        "city": "Columbia",
        "startDate": "2023-12-16",
        "endDate": "2023-12-17",
        "date": "2023-12-16 - 2023-12-17",
        "url": "https://www.eventbrite.com/e/24k-magic-holiday-extravagazza-tickets-734006542327",
        "location": {
            "address": {
                "addressCountry": "US",
                "addressLocality": "Columbia",
                "addressRegion": "SC",
                "streetAddress": "1200 Rosewood Drive",
                "postalCode": "29201",
                "@type": "PostalAddress"
            },
            "geo": {
                "latitude": "33.9770371",
                "@type": "GeoCoordinates",
                "longitude": "-81.0209153"
            },
            "@type": "Place",
            "name": "South Carolina State Fair"
        },
        "address": {
            "addressCountry": "US",
            "addressLocality": "Columbia",
            "addressRegion": "SC",
            "streetAddress": "1200 Rosewood Drive",
            "postalCode": "29201",
            "@type": "PostalAddress"
        },
        "description": "Come celebrate the holidays with us and help support the James R Clark Memorial Sickle Cell Foundation.",
        "position": {
            "lat": 33.9770371,
            "lng": -81.0209153
        }
    },
    {
        "name": "Group Therapy's 34th Chili Cook-Off",
        "city": "Columbia",
        "startDate": "2023-12-02",
        "endDate": "2023-12-02",
        "date": "2023-12-02",
        "url": "https://www.eventbrite.com/e/group-therapys-34th-chili-cook-off-tickets-728031871927",
        "location": {
            "address": {
                "addressCountry": "US",
                "addressLocality": "Columbia",
                "addressRegion": "SC",
                "streetAddress": "2107 Greene Street",
                "postalCode": "29205",
                "@type": "PostalAddress"
            },
            "geo": {
                "latitude": "34.0006684",
                "@type": "GeoCoordinates",
                "longitude": "-81.0162608"
            },
            "@type": "Place",
            "name": "2107 Greene St"
        },
        "address": {
            "addressCountry": "US",
            "addressLocality": "Columbia",
            "addressRegion": "SC",
            "streetAddress": "2107 Greene Street",
            "postalCode": "29205",
            "@type": "PostalAddress"
        },
        "description": "Welcome contestants! All three team packages are available for purchase here.",
        "position": {
            "lat": 34.0006684,
            "lng": -81.0162608
        }
    },
    {
        "name": "7th Annual Winter Fest Toy Giveway",
        "city": "Columbia",
        "startDate": "2023-12-02",
        "endDate": "2023-12-02",
        "date": "2023-12-02",
        "url": "https://www.eventbrite.com/e/7th-annual-winter-fest-toy-giveway-tickets-653141352367",
        "location": {
            "address": {
                "addressCountry": "US",
                "addressLocality": "Columbia",
                "addressRegion": "SC",
                "streetAddress": "4646 HardScrabble Road",
                "postalCode": "29229",
                "@type": "PostalAddress"
            },
            "geo": {
                "latitude": "34.1562284",
                "@type": "GeoCoordinates",
                "longitude": "-80.9110304"
            },
            "@type": "Place",
            "name": "Rehoboth Baptist Church Family Life Center"
        },
        "address": {
            "addressCountry": "US",
            "addressLocality": "Columbia",
            "addressRegion": "SC",
            "streetAddress": "4646 HardScrabble Road",
            "postalCode": "29229",
            "@type": "PostalAddress"
        },
        "description": "Embrace the season with holiday music, community resources, play holiday-themed games, free toys, lite refreshments, and much more.",
        "position": {
            "lat": 34.1562284,
            "lng": -80.9110304
        }
    },
    {
        "name": "Tranquility Transitional Housing First Aunnual Public Benefit Fundraiser",
        "city": "Columbia",
        "startDate": "2023-11-24",
        "endDate": "2023-11-25",
        "date": "2023-11-24 - 2023-11-25",
        "url": "https://www.eventbrite.com/e/tranquility-transitional-housing-first-aunnual-public-benefit-fundraiser-tickets-738292351297",
        "location": {
            "address": {
                "addressCountry": "US",
                "addressLocality": "Gadsden",
                "addressRegion": "SC",
                "streetAddress": "1032 George Wilson Boulevard",
                "postalCode": "29052",
                "@type": "PostalAddress"
            },
            "geo": {
                "latitude": "33.8244251",
                "@type": "GeoCoordinates",
                "longitude": "-80.70178179999999"
            },
            "@type": "Place",
            "name": "1032 George Wilson Blvd"
        },
        "address": {
            "addressCountry": "US",
            "addressLocality": "Gadsden",
            "addressRegion": "SC",
            "streetAddress": "1032 George Wilson Boulevard",
            "postalCode": "29052",
            "@type": "PostalAddress"
        },
        "description": "The purpose of this fundraiser event is to build a facility for housing and educate and decriminalized ex offenders.",
        "position": {
            "lat": 33.8244251,
            "lng": -80.70178179999999
        }
    },
    {
        "name": "THE VULNERABILITY PROJECT",
        "city": "Columbia",
        "startDate": "2023-11-19",
        "endDate": "2023-11-19",
        "date": "2023-11-19",
        "url": "https://www.eventbrite.com/e/the-vulnerability-project-tickets-742980854737",
        "location": {
            "address": {
                "addressCountry": "US",
                "addressLocality": "Columbia",
                "addressRegion": "SC",
                "streetAddress": "200 Graces Way",
                "postalCode": "29229",
                "@type": "PostalAddress"
            },
            "geo": {
                "latitude": "34.1134025",
                "@type": "GeoCoordinates",
                "longitude": "-80.88164990000001"
            },
            "@type": "Place",
            "name": "Mimsy’s Kitchen & Jazz Lounge"
        },
        "address": {
            "addressCountry": "US",
            "addressLocality": "Columbia",
            "addressRegion": "SC",
            "streetAddress": "200 Graces Way",
            "postalCode": "29229",
            "@type": "PostalAddress"
        },
        "description": "Discussion about vulnerability in relationships",
        "position": {
            "lat": 34.1134025,
            "lng": -80.88164990000001
        }
    },
    {
        "name": "Girl I Got You Christmas Give- A-Thon",
        "city": "Columbia",
        "startDate": "2023-12-09",
        "endDate": "2023-12-09",
        "date": "2023-12-09",
        "url": "https://www.eventbrite.com/e/girl-i-got-you-christmas-give-a-thon-tickets-753853996597",
        "location": {
            "address": {
                "addressCountry": "US",
                "addressLocality": "Hartsville",
                "addressRegion": "SC",
                "streetAddress": "1103 South 6th Street",
                "postalCode": "29550",
                "@type": "PostalAddress"
            },
            "geo": {
                "latitude": "34.3588349",
                "@type": "GeoCoordinates",
                "longitude": "-80.0694262"
            },
            "@type": "Place",
            "name": "1103 South 6th Street, Hartsville, SC, USA"
        },
        "address": {
            "addressCountry": "US",
            "addressLocality": "Hartsville",
            "addressRegion": "SC",
            "streetAddress": "1103 South 6th Street",
            "postalCode": "29550",
            "@type": "PostalAddress"
        },
        "description": "Hey girl, get ready for the ultimate Christmas Give-A-Thon where we'll shower you with gifts and spread the holiday cheer in person!",
        "position": {
            "lat": 34.3588349,
            "lng": -80.0694262
        }
    },
    {
        "name": "Bloodies and Bagels",
        "city": "Columbia",
        "startDate": "2023-11-23",
        "endDate": "2023-11-23",
        "date": "2023-11-23",
        "url": "https://www.eventbrite.com/e/bloodies-and-bagels-tickets-662502772627",
        "location": {
            "address": {
                "addressCountry": "US",
                "addressLocality": "Aiken",
                "addressRegion": "SC",
                "streetAddress": "433 Newberry Street Southwest",
                "postalCode": "29801",
                "@type": "PostalAddress"
            },
            "geo": {
                "latitude": "33.5547367",
                "@type": "GeoCoordinates",
                "longitude": "-81.72527439999999"
            },
            "@type": "Place",
            "name": "Aiken County Historical Museum"
        },
        "address": {
            "addressCountry": "US",
            "addressLocality": "Aiken",
            "addressRegion": "SC",
            "streetAddress": "433 Newberry Street Southwest",
            "postalCode": "29801",
            "@type": "PostalAddress"
        },
        "description": "Free outdoor community fund raiser for MHA of Aiken. Bagels, Bloody Marys, coffee, cider & live music. Tickets are required for each person!",
        "position": {
            "lat": 33.5547367,
            "lng": -81.72527439999999
        }
    },
    {
        "name": "Volunteer Advocate Training",
        "city": "Columbia",
        "startDate": "2023-12-05",
        "endDate": "2023-12-05",
        "date": "2023-12-05",
        "url": "https://www.eventbrite.com/e/volunteer-advocate-training-tickets-740094972987",
        "location": {
            "address": {
                "addressCountry": "US",
                "addressLocality": "Greenwood",
                "addressRegion": "SC",
                "streetAddress": "115 East Alexander Avenue",
                "postalCode": "29646",
                "@type": "PostalAddress"
            },
            "geo": {
                "latitude": "34.17894199999999",
                "@type": "GeoCoordinates",
                "longitude": "-82.151382"
            },
            "@type": "Place",
            "name": "Beyond Abuse"
        },
        "address": {
            "addressCountry": "US",
            "addressLocality": "Greenwood",
            "addressRegion": "SC",
            "streetAddress": "115 East Alexander Avenue",
            "postalCode": "29646",
            "@type": "PostalAddress"
        },
        "description": "Beyond Abuse offers training for volunteer advocates who wish to help those impacted by sexual violence and child abuse.",
        "position": {
            "lat": 34.17894199999999,
            "lng": -82.151382
        }
    },
    {
        "name": "Annual Charity Gala",
        "city": "Columbia",
        "startDate": "2023-12-16",
        "endDate": "2023-12-16",
        "date": "2023-12-16",
        "url": "https://www.eventbrite.com/e/annual-charity-gala-tickets-744441784417",
        "location": {
            "address": {
                "addressCountry": "US",
                "addressLocality": "Rock Hill",
                "addressRegion": "SC",
                "streetAddress": "742 North Anderson Road",
                "postalCode": "29730",
                "@type": "PostalAddress"
            },
            "geo": {
                "latitude": "34.9572439",
                "@type": "GeoCoordinates",
                "longitude": "-80.99517929999999"
            },
            "@type": "Place",
            "name": "742 North Anderson Road, Rock Hill, SC, USA"
        },
        "address": {
            "addressCountry": "US",
            "addressLocality": "Rock Hill",
            "addressRegion": "SC",
            "streetAddress": "742 North Anderson Road",
            "postalCode": "29730",
            "@type": "PostalAddress"
        },
        "description": "Join us for the Annual Charity Gala, an unforgettable evening of giving, glitz, and glamour, where we come together to make a difference in",
        "position": {
            "lat": 34.9572439,
            "lng": -80.99517929999999
        }
    },
    {
        "name": "Volunteer Event",
        "city": "Columbia",
        "startDate": "2023-12-16",
        "endDate": "2023-12-16",
        "date": "2023-12-16",
        "url": "https://www.eventbrite.com/e/volunteer-event-tickets-757531596397",
        "location": {
            "address": {
                "addressCountry": "US",
                "addressLocality": "Charlotte",
                "addressRegion": "NC",
                "streetAddress": "500-A Spratt Street",
                "postalCode": "28206",
                "@type": "PostalAddress"
            },
            "geo": {
                "latitude": "35.2384999",
                "@type": "GeoCoordinates",
                "longitude": "-80.8378271"
            },
            "@type": "Place",
            "name": "Crisis Assistance Ministry"
        },
        "address": {
            "addressCountry": "US",
            "addressLocality": "Charlotte",
            "addressRegion": "NC",
            "streetAddress": "500-A Spratt Street",
            "postalCode": "28206",
            "@type": "PostalAddress"
        },
        "description": "Join NBMBAA for a volunteer event at the Crisis Assistance Ministry.",
        "position": {
            "lat": 35.2384999,
            "lng": -80.8378271
        }
    },
    {
        "name": "Women’s Conference",
        "city": "Columbia",
        "startDate": "2024-03-23",
        "endDate": "2024-03-23",
        "date": "2024-03-23",
        "url": "https://www.eventbrite.com/e/womens-conference-tickets-722511349897",
        "location": {
            "address": {
                "addressCountry": "US",
                "addressLocality": "Florence",
                "addressRegion": "SC",
                "streetAddress": "Florence, SC, USA",
                "postalCode": "",
                "@type": "PostalAddress"
            },
            "geo": {
                "latitude": "34.1954331",
                "@type": "GeoCoordinates",
                "longitude": "-79.7625625"
            },
            "@type": "Place",
            "name": "Florence, SC, USA"
        },
        "address": {
            "addressCountry": "US",
            "addressLocality": "Florence",
            "addressRegion": "SC",
            "streetAddress": "Florence, SC, USA",
            "postalCode": "",
            "@type": "PostalAddress"
        },
        "description": "Get ready for a powerful gathering of inspiring women at our Women's Conference on March 23, 2024, where we celebrate, empower, and uplift!",
        "position": {
            "lat": 34.1954331,
            "lng": -79.7625625
        }
    },
    {
        "name": "Party in Purple",
        "city": "Columbia",
        "startDate": "2023-11-24",
        "endDate": "2023-11-25",
        "date": "2023-11-24 - 2023-11-25",
        "url": "https://www.eventbrite.com/e/party-in-purple-tickets-732472955327",
        "location": {
            "address": {
                "addressCountry": "US",
                "addressLocality": "Cheraw",
                "addressRegion": "SC",
                "streetAddress": "1 Village Park",
                "postalCode": "29520",
                "@type": "PostalAddress"
            },
            "geo": {
                "latitude": "34.6989272",
                "@type": "GeoCoordinates",
                "longitude": "-79.88315759999999"
            },
            "@type": "Place",
            "name": "Cypress Music Hall, Village Park, Cheraw, SC, USA"
        },
        "address": {
            "addressCountry": "US",
            "addressLocality": "Cheraw",
            "addressRegion": "SC",
            "streetAddress": "1 Village Park",
            "postalCode": "29520",
            "@type": "PostalAddress"
        },
        "description": "The Purple Crusaders are hosting our 1st annual fundraising event to raise awareness for Alzheimer's.",
        "position": {
            "lat": 34.6989272,
            "lng": -79.88315759999999
        }
    },
    {
        "name": "Thanksgiving GIVE BACK",
        "city": "Columbia",
        "startDate": "2023-11-20",
        "endDate": "2023-11-20",
        "date": "2023-11-20",
        "url": "https://www.eventbrite.com/e/thanksgiving-give-back-tickets-750265292687",
        "location": {
            "address": {
                "addressCountry": "US",
                "addressLocality": "Charlotte",
                "addressRegion": "NC",
                "streetAddress": "210 East Trade Street",
                "postalCode": "28202",
                "@type": "PostalAddress"
            },
            "geo": {
                "latitude": "35.2255999",
                "@type": "GeoCoordinates",
                "longitude": "-80.8419128"
            },
            "@type": "Place",
            "name": "The MilliUp Event Center"
        },
        "address": {
            "addressCountry": "US",
            "addressLocality": "Charlotte",
            "addressRegion": "NC",
            "streetAddress": "210 East Trade Street",
            "postalCode": "28202",
            "@type": "PostalAddress"
        },
        "description": "20 Families will receive Free Thanksgiving Dinners.",
        "position": {
            "lat": 35.2255999,
            "lng": -80.8419128
        }
    },
    {
        "name": "Hanukkah Concert",
        "city": "Columbia",
        "startDate": "2023-12-08",
        "endDate": "2023-12-08",
        "date": "2023-12-08",
        "url": "https://www.eventbrite.com/e/hanukkah-concert-tickets-757002885007",
        "location": {
            "address": {
                "addressCountry": "US",
                "addressLocality": "Charlotte",
                "addressRegion": "NC",
                "streetAddress": "6040 Woodleigh Oaks Drive",
                "postalCode": "28226",
                "@type": "PostalAddress"
            },
            "geo": {
                "latitude": "35.0862681",
                "@type": "GeoCoordinates",
                "longitude": "-80.82580879999999"
            },
            "@type": "Place",
            "name": "Rea Woods Club House"
        },
        "address": {
            "addressCountry": "US",
            "addressLocality": "Charlotte",
            "addressRegion": "NC",
            "streetAddress": "6040 Woodleigh Oaks Drive",
            "postalCode": "28226",
            "@type": "PostalAddress"
        },
        "description": "Experience the power of live music as we showcase compositions by Jewish, Ukrainian, French, and American artists.",
        "position": {
            "lat": 35.0862681,
            "lng": -80.82580879999999
        }
    },
    {
        "name": "New Hope End of Year Celebration",
        "city": "Columbia",
        "startDate": "2023-12-01",
        "endDate": "2023-12-01",
        "date": "2023-12-01",
        "url": "https://www.eventbrite.com/e/new-hope-end-of-year-celebration-tickets-740366374757",
        "location": {
            "address": {
                "addressCountry": "US",
                "addressLocality": "Rock Hill",
                "addressRegion": "SC",
                "streetAddress": "140 East Main Street",
                "postalCode": "29730",
                "@type": "PostalAddress"
            },
            "geo": {
                "latitude": "34.92520199999999",
                "@type": "GeoCoordinates",
                "longitude": "-81.0269266"
            },
            "@type": "Place",
            "name": "Crystal Ballroom Rock Hill, East Main Street, Rock Hill, SC, USA"
        },
        "address": {
            "addressCountry": "US",
            "addressLocality": "Rock Hill",
            "addressRegion": "SC",
            "streetAddress": "140 East Main Street",
            "postalCode": "29730",
            "@type": "PostalAddress"
        },
        "description": "Join us at the New Hope End of Year Celebration for a night of joy, laughter, and new beginnings as we bid farewell to the old and welcome t",
        "position": {
            "lat": 34.92520199999999,
            "lng": -81.0269266
        }
    },
    {
        "name": "IDS Charlotte Holiday Charity Cocktail Event",
        "city": "Columbia",
        "startDate": "2023-12-13",
        "endDate": "2023-12-13",
        "date": "2023-12-13",
        "url": "https://www.eventbrite.com/e/ids-charlotte-holiday-charity-cocktail-event-tickets-745709756957",
        "location": {
            "address": {
                "addressCountry": "US",
                "addressLocality": "Charlotte",
                "addressRegion": "NC",
                "streetAddress": "400 Hermitage Road",
                "postalCode": "28207",
                "@type": "PostalAddress"
            },
            "geo": {
                "latitude": "35.20152699999999",
                "@type": "GeoCoordinates",
                "longitude": "-80.82749199999999"
            },
            "@type": "Place",
            "name": "The Duke Mansion"
        },
        "address": {
            "addressCountry": "US",
            "addressLocality": "Charlotte",
            "addressRegion": "NC",
            "streetAddress": "400 Hermitage Road",
            "postalCode": "28207",
            "@type": "PostalAddress"
        },
        "description": "Come spend a joyous evening as we celebrate IDS Charlotte for our Annual Holiday Event",
        "position": {
            "lat": 35.20152699999999,
            "lng": -80.82749199999999
        }
    },
    {
        "name": "Elvis for the Children (Charity Event)",
        "city": "Columbia",
        "startDate": "2023-12-10",
        "endDate": "2023-12-10",
        "date": "2023-12-10",
        "url": "https://www.eventbrite.com/e/elvis-for-the-children-charity-event-tickets-734416137437",
        "location": {
            "address": {
                "addressCountry": "US",
                "addressLocality": "Charlotte",
                "addressRegion": "NC",
                "streetAddress": "5200 Mecklenburg Shrine Club Road",
                "postalCode": "28215",
                "@type": "PostalAddress"
            },
            "geo": {
                "latitude": "35.2442101",
                "@type": "GeoCoordinates",
                "longitude": "-80.655365"
            },
            "@type": "Place",
            "name": "Mecklenburg Shrine Club"
        },
        "address": {
            "addressCountry": "US",
            "addressLocality": "Charlotte",
            "addressRegion": "NC",
            "streetAddress": "5200 Mecklenburg Shrine Club Road",
            "postalCode": "28215",
            "@type": "PostalAddress"
        },
        "description": "Let's rock 'n' roll for a great cause at Elvis for the Children, a charity event where we'll raise funds to support Shriners Children's",
        "position": {
            "lat": 35.2442101,
            "lng": -80.655365
        }
    },
    {
        "name": "CYPGala - Charlotte Young Professionals Group’s Black-Tie Charity Gala",
        "city": "Columbia",
        "startDate": "2023-12-01",
        "endDate": "2023-12-01",
        "date": "2023-12-01",
        "url": "https://www.eventbrite.com/e/cypgala-charlotte-young-professionals-groups-black-tie-charity-gala-tickets-754202448827",
        "location": {
            "address": {
                "addressCountry": "US",
                "addressLocality": "Charlotte",
                "addressRegion": "NC",
                "streetAddress": "400 East Martin Luther King Junior Boulevard",
                "postalCode": "28202",
                "@type": "PostalAddress"
            },
            "geo": {
                "latitude": "35.22113660000001",
                "@type": "GeoCoordinates",
                "longitude": "-80.8439538"
            },
            "@type": "Place",
            "name": "NASCAR Hall of Fame, East Martin Luther King Junior Boulevard, Charlotte, NC, USA"
        },
        "address": {
            "addressCountry": "US",
            "addressLocality": "Charlotte",
            "addressRegion": "NC",
            "streetAddress": "400 East Martin Luther King Junior Boulevard",
            "postalCode": "28202",
            "@type": "PostalAddress"
        },
        "description": "Join us on December 1 to celebrate 2023’s wins, meet likeminded emerging leaders, and make a lasting impact on the Charlotte community!",
        "position": {
            "lat": 35.22113660000001,
            "lng": -80.8439538
        }
    },
    {
        "name": "Copy of \"Mission Possible: A Mindful Fundraiser\"",
        "city": "Columbia",
        "startDate": "2024-04-21",
        "endDate": "2024-04-21",
        "date": "2024-04-21",
        "url": "https://www.eventbrite.com/e/copy-of-mission-possible-a-mindful-fundraiser-tickets-754600479347",
        "location": {
            "address": {
                "addressCountry": "US",
                "addressLocality": "Charlotte",
                "addressRegion": "NC",
                "streetAddress": "4125 Yancey Road",
                "postalCode": "28217",
                "@type": "PostalAddress"
            },
            "geo": {
                "latitude": "35.186857",
                "@type": "GeoCoordinates",
                "longitude": "-80.880757"
            },
            "@type": "Place",
            "name": "Queen Park Social, Yancey Road, Charlotte, NC, USA"
        },
        "address": {
            "addressCountry": "US",
            "addressLocality": "Charlotte",
            "addressRegion": "NC",
            "streetAddress": "4125 Yancey Road",
            "postalCode": "28217",
            "@type": "PostalAddress"
        },
        "description": "Unleash fun with purpose at Mission Possible: A Mindful Fundraiser! Join us at Queen Park Social for a SUNDAY FUNDAY of play and purpose.",
        "position": {
            "lat": 35.186857,
            "lng": -80.880757
        }
    },
    {
        "name": "DRAGO Charities- Benefiting Hearts United for Good (HUG)",
        "city": "Columbia",
        "startDate": "2023-11-21",
        "endDate": "2023-11-21",
        "date": "2023-11-21",
        "url": "https://www.eventbrite.com/e/drago-charities-benefiting-hearts-united-for-good-hug-tickets-748816529397",
        "location": {
            "address": {
                "addressCountry": "US",
                "addressLocality": "Charlotte",
                "addressRegion": "NC",
                "streetAddress": "1221 The Plaza",
                "postalCode": "28205",
                "@type": "PostalAddress"
            },
            "geo": {
                "latitude": "35.21923",
                "@type": "GeoCoordinates",
                "longitude": "-80.8113"
            },
            "@type": "Place",
            "name": "Single Barrel Room"
        },
        "address": {
            "addressCountry": "US",
            "addressLocality": "Charlotte",
            "addressRegion": "NC",
            "streetAddress": "1221 The Plaza",
            "postalCode": "28205",
            "@type": "PostalAddress"
        },
        "description": "Not your grandmas bingo, We do this for shitty prizes, fun and most importantly CHARITY!!",
        "position": {
            "lat": 35.21923,
            "lng": -80.8113
        }
    }
]